{
  "swagger" : "2.0",
  "info" : {
    "version" : "v1",
    "title" : "Currency Converter CHF API"
  },
  "host" : "localhost:8082",
  "basePath" : "/currency-converter-chf",
  "schemes" : [ "http" ],
  "paths" : {
    "/currencyConverterChfService/convertMoney" : {
      "post" : {
        "summary" : "Convert money.",
        "description" : "",
        "operationId" : "convertMoney",
        "consumes" : [ "application/xml", "application/json", "text/xml" ],
        "produces" : [ "application/xml", "application/json" ],
        "parameters" : [ {
          "in" : "body",
          "name" : "body",
          "description" : "Value to convert.",
          "required" : false,
          "schema" : {
            "$ref" : "#/definitions/ConvertIn"
          }
        }, {
          "name" : "X-JLNS-API-ID",
          "in" : "header",
          "description" : "API ID to tell server which facade to use.",
          "required" : false,
          "type" : "string"
        }, {
          "name" : "X-JLNS-Privilege-Names",
          "in" : "header",
          "description" : "List of privileged names separated by semicolon used with JLupinPermissionResolver to check if call is privileged.",
          "required" : false,
          "type" : "string"
        }, {
          "name" : "X-JLNS-Locale",
          "in" : "header",
          "description" : "Locale for translation.",
          "required" : false,
          "type" : "string"
        }, {
          "name" : "X-JLNS-Sequence-Name",
          "in" : "header",
          "description" : "Sequence name to use for deserializing method parameters.",
          "required" : false,
          "type" : "string"
        }, {
          "name" : "X-JLNS-Request-ID",
          "in" : "header",
          "description" : "Request ID.",
          "required" : false,
          "type" : "string"
        }, {
          "name" : "X-JLNS-Session-ID",
          "in" : "header",
          "description" : "Session ID.",
          "required" : false,
          "type" : "string"
        }, {
          "name" : "X-JLNS-User",
          "in" : "header",
          "description" : "User.",
          "required" : false,
          "type" : "string"
        }, {
          "name" : "X-JLNS-Client-Application-Name",
          "in" : "header",
          "description" : "Client application name.",
          "required" : false,
          "type" : "string"
        }, {
          "name" : "X-JLNS-IP",
          "in" : "header",
          "description" : "IP address.",
          "required" : false,
          "type" : "string"
        }, {
          "name" : "X-JLNS-Monitoring-ID",
          "in" : "header",
          "description" : "Monitoring ID.",
          "required" : false,
          "type" : "string"
        } ],
        "responses" : {
          "200" : {
            "description" : "successful operation",
            "schema" : {
              "$ref" : "#/definitions/ConvertOut"
            }
          },
          "default" : {
            "description" : "Default error response",
            "schema" : {
              "$ref" : "#/definitions/jLupinExceptionModel"
            }
          }
        }
      }
    }
  },
  "definitions" : {
    "ConvertIn" : {
      "type" : "object",
      "properties" : {
        "value" : {
          "type" : "number"
        },
        "from" : {
          "type" : "string",
          "enum" : [ "USD", "EUR", "GBP", "CHF" ]
        },
        "to" : {
          "type" : "string",
          "enum" : [ "USD", "EUR", "GBP", "CHF" ]
        }
      }
    },
    "ConvertOut" : {
      "type" : "object",
      "properties" : {
        "value" : {
          "type" : "number"
        },
        "currency" : {
          "type" : "string",
          "enum" : [ "USD", "EUR", "GBP", "CHF" ]
        }
      }
    },
    "jLupinExceptionModel" : {
      "type" : "object",
      "properties" : {
        "errorMessage" : {
          "type" : "string"
        },
        "errorCode" : {
          "type" : "string"
        },
        "errorHttpResponseStatus" : {
          "type" : "string"
        },
        "errorReasons" : {
          "type" : "array",
          "items" : {
            "type" : "string"
          }
        },
        "errorSolutions" : {
          "type" : "array",
          "items" : {
            "type" : "string"
          }
        },
        "sourceStackTrace" : {
          "type" : "string"
        },
        "additionalErrorCodeMap" : {
          "type" : "object",
          "additionalProperties" : {
            "type" : "object"
          }
        },
        "throwableAsByteArray" : {
          "type" : "array",
          "items" : {
            "type" : "string",
            "format" : "byte"
          }
        }
      }
    }
  }
}